gba_tiler.py
gba_tiler-1.6.1.dist-info/licenses/LICENSE
gba_tiler-1.6.1.dist-info/METADATA
gba_tiler-1.6.1.dist-info/WHEEL
gba_tiler-1.6.1.dist-info/entry_points.txt
gba_tiler-1.6.1.dist-info/top_level.txt
gba_tiler-1.6.1.dist-info/RECORD
