Metadata-Version: 2.4
Name: gba-tiler
Version: 1.6.1
Summary: High-performance tool for downloading and tiling GlobalBuildingAtlas data
Home-page: https://gitlab.rlp.net/druee/gba-tiler
Author: Clemens Drüe
Author-email: Clemens Drüe <druee@uni-trier.de>
License: EUPL-1.2
Project-URL: Homepage, https://gitlab.rlp.net/druee/gba-tiler
Project-URL: Documentation, https://gitlab.rlp.net/druee/gba-tiler/-/blob/main/README.md
Project-URL: Repository, https://gitlab.rlp.net/druee/gba-tiler
Project-URL: Bug Tracker, https://gitlab.rlp.net/druee/gba-tiler/-/issues
Keywords: GIS,building-footprints,geojson,spatial-data,tiling
Classifier: Development Status :: 4 - Beta
Classifier: Intended Audience :: Science/Research
Classifier: License :: OSI Approved :: European Union Public Licence 1.2 (EUPL 1.2)
Classifier: Operating System :: OS Independent
Classifier: Programming Language :: Python :: 3
Classifier: Programming Language :: Python :: 3.8
Classifier: Programming Language :: Python :: 3.9
Classifier: Programming Language :: Python :: 3.10
Classifier: Programming Language :: Python :: 3.11
Classifier: Programming Language :: Python :: 3.12
Classifier: Topic :: Scientific/Engineering :: GIS
Classifier: Topic :: Utilities
Requires-Python: >=3.8
License-File: LICENSE
Requires-Dist: ijson>=3.1.0
Requires-Dist: requests>=2.25.0
Requires-Dist: GDAL>=3.0.0
Provides-Extra: dev
Requires-Dist: setuptools_scm; extra == "dev"
Requires-Dist: build; extra == "dev"
Requires-Dist: twine; extra == "dev"
Requires-Dist: pytest; extra == "dev"
Dynamic: author
Dynamic: home-page
Dynamic: license-file
Dynamic: requires-python
